kde_account_oauth_client/__init__.py
kde_account_oauth_client/admin.py
kde_account_oauth_client/apps.py
kde_account_oauth_client/management/__init__.py
kde_account_oauth_client/management/commands/__init__.py
kde_account_oauth_client/management/commands/makesuperuser.py
kde_account_oauth_client/migrations/0001_initial.py
kde_account_oauth_client/migrations/0002_oauth_user_info.py
kde_account_oauth_client/migrations/__init__.py
kde_account_oauth_client/models.py
kde_account_oauth_client/signals.py
kde_account_oauth_client/templates/blender_id_oauth_client/login_loop_detected.html
kde_account_oauth_client/urls.py
kde_account_oauth_client/views.py
kde_account_oauth_client-0.9.4.dist-info/LICENSE
kde_account_oauth_client-0.9.4.dist-info/WHEEL
kde_account_oauth_client-0.9.4.dist-info/METADATA
kde_account_oauth_client-0.9.4.dist-info/RECORD
