Metadata-Version: 2.1
Name: kde-account-oauth-client
Version: 0.9.4
Summary: Django app for using KDE Account as OAuth2 authentication service.
Home-page: https://gitlab.com/blender-institute/kde-account-oauth-client
License: GPL-2.0
Author: Sybren A. Stüvel
Author-email: sybren@blender.studio
Requires-Python: >=3.6,<4.0
Classifier: Environment :: Web Environment
Classifier: Framework :: Django
Classifier: Framework :: Django :: 3.0
Classifier: Intended Audience :: Developers
Classifier: License :: OSI Approved :: GNU General Public License v2 (GPLv2)
Classifier: Operating System :: OS Independent
Classifier: Programming Language :: Python :: 3
Classifier: Programming Language :: Python :: 3.6
Classifier: Programming Language :: Python :: 3.7
Classifier: Programming Language :: Python :: 3.8
Classifier: Topic :: Internet :: WWW/HTTP
Requires-Dist: Django (>=2.1,<3.1.0)
Requires-Dist: requests-oauthlib (>=1.0,<2.0)
